{
  "date": "2024-10-05 (六) 14:00 - 16:00",
  "title": "我的第一個獸設！(2024-10-05)",
  "location": "第二學生活動中心（二活）604教室",
  "preview": "/events/我的第一個獸設！(2024-10-05)/preview.jpg",
  "image": "/events/我的第一個獸設！(2024-10-05)/image.jpg",
  "content": "「獸設（Fursona）」是獸文化同好間耳熟能詳的術語，相當於動漫圈常聽到的「人設（Persona）」，只是媒介變為獸或是獸人，用於在社群中代表自己、和他人互動。<br>想必剛入圈的朋友們都有過看到別人帥氣、漂亮或可愛的獸設，便開始希望可以有一個屬於自己的設定，卻因為不知如何開始，只能將自己的設定停留在構想階段的經驗。<br>這次社課我們邀請了數位社員來和大家分享自己的獸設！<br>如果想知道獸設怎麼從無到有出現，或是想汲取一些靈感來創造屬於自己的設定，就趕快填寫下面的報名表單吧！<br>※ 如果你也想要上台分享自己的獸設的話，可以在表單內上傳自己需要用到的圖片，並在備註欄和我們說預計要講多久，我們會依人數預留時間給你分享喔！<br>​<br>✨活動名稱：我的第一個獸設！<br>🏰主辦單位：臺大獸文化交流社<br>🗓️活動時間：10/05（六） 14：00～16：00（13：30開放進場）<br>📍活動地點：臺大第二學生活動中心 604 教室<br>💰參加費用：免費！",
  "links": [
    {
      "name": "報名表單",
      "link": "https://forms.gle/ZzB9aXBwERyMmxXH9"
    }
  ]
}